kittyscript/__init__.py
Kittyscript-2.9.8.dist-info/LICENCE.txt
Kittyscript-2.9.8.dist-info/METADATA
Kittyscript-2.9.8.dist-info/WHEEL
Kittyscript-2.9.8.dist-info/top_level.txt
Kittyscript-2.9.8.dist-info/RECORD
