Metadata-Version: 2.1
Name: Kittyscript
Version: 2.9.8
Summary: Assist mode for python
Home-page: https://github.com/Iwertyuiop123653/kitty-script-
Author: Anahad Khosa
Author-email: hahacoolguystaco@gmail.com
License: MIT
Keywords: Assist mode
Platform: UNKNOWN
Classifier: Development Status :: 5 - Production/Stable
Classifier: Intended Audience :: Education
Classifier: Operating System :: Microsoft :: Windows :: Windows 10
Classifier: License :: OSI Approved :: MIT License
Classifier: Programming Language :: Python :: 3
License-File: LICENCE.txt
Requires-Dist: keyboard
Requires-Dist: qrcode
